lemon_rag/__init__.py
lemon_rag/api/__init__.py
lemon_rag/api/auth.py
lemon_rag/api/base.py
lemon_rag/api/business.py
lemon_rag/api/chat.py
lemon_rag/api/dev.py
lemon_rag/api/local.py
lemon_rag/configs/__init__.py
lemon_rag/configs/api_config.py
lemon_rag/configs/local_dev_config.py
lemon_rag/core/__init__.py
lemon_rag/core/executor_pool.py
lemon_rag/dependencies/__init__.py
lemon_rag/dependencies/data_access.py
lemon_rag/dependencies/vector_access.py
lemon_rag/lemon_runtime/__init__.py
lemon_rag/lemon_runtime/models.py
lemon_rag/lemon_runtime/models_template.py
lemon_rag/lemon_runtime/wrappers.py
lemon_rag/llm/__init__.py
lemon_rag/llm/agents/__init__.py
lemon_rag/llm/agents/interactive_functions/base_function.py
lemon_rag/llm/agents/interactive_functions/data_query_functions.py
lemon_rag/llm/agents/interactive_functions/form_record.py
lemon_rag/llm/agents/prompts/__init__.py
lemon_rag/llm/agents/prompts/ai_assistent_agent.py
lemon_rag/llm/agents/prompts/form_record.py
lemon_rag/llm/agents/prompts/select_query_command.py
lemon_rag/llm/agents/prompts/standard_query_agent.py
lemon_rag/llm/agents/prompts/summarize.py
lemon_rag/llm/agents/rag/__init__.py
lemon_rag/llm/agents/rag/example.txt
lemon_rag/llm/agents/rag/retrieval/__init__.py
lemon_rag/llm/agents/rag/retrieval/retrieve_candidate.py
lemon_rag/llm/agents/rag/retrieval/retrieve_messages.py
lemon_rag/llm/agents/rag/retrieval/retrive_knowledgebase.py
lemon_rag/llm/agents/rag/vectorization/FileVectorization.py
lemon_rag/llm/agents/rag/vectorization/__init__.py
lemon_rag/llm/agents/rag/vectorization/content_extractor.py
lemon_rag/llm/agents/rag/vectorization/runner.py
lemon_rag/llm/callback_handlers/__init__.py
lemon_rag/llm/callback_handlers/base_handler.py
lemon_rag/llm/callback_handlers/form_callback_handler.py
lemon_rag/llm/callback_handlers/io_utils.py
lemon_rag/llm/callback_handlers/text_callback_handler.py
lemon_rag/llm/client/__init__.py
lemon_rag/llm/client/base_client.py
lemon_rag/llm/client/memory.py
lemon_rag-0.1.743.dist-info/METADATA
lemon_rag-0.1.743.dist-info/WHEEL
lemon_rag-0.1.743.dist-info/RECORD
