Metadata-Version: 2.1
Name: lemon-rag
Version: 0.1.743
Summary: 
Author: Your Name
Author-email: you@example.com
Requires-Python: >=3.8.1,<4.0
Classifier: Programming Language :: Python :: 3
Classifier: Programming Language :: Python :: 3.9
Classifier: Programming Language :: Python :: 3.10
Classifier: Programming Language :: Python :: 3.11
Classifier: Programming Language :: Python :: 3.12
Requires-Dist: aiohttp (>=3.9.1,<4.0.0)
Requires-Dist: ijson (>=3.2.3,<4.0.0)
Requires-Dist: langchain (==0.0.352)
Requires-Dist: langchain-core (==0.1.3)
Requires-Dist: openai (==0.27.10)
Requires-Dist: pdf2docx (>=0.5.7,<0.6.0)
Requires-Dist: pdfplumber (>=0.10.3,<0.11.0)
Requires-Dist: peewee (>=3.13.2,<4.0.0)
Requires-Dist: pydantic (==1.10.12)
Requires-Dist: pydantic-i18n (>=0.4.0,<0.5.0)
Requires-Dist: pydocx (>=0.9.10,<0.10.0)
Requires-Dist: pymilvus (==2.3.4)
Requires-Dist: pytest (>=7.4.4,<8.0.0)
Requires-Dist: requests (>=2.31.0,<3.0.0)
Requires-Dist: sanic (==19.12.2)
Requires-Dist: tiktoken (==0.5.2)
Requires-Dist: typing_extensions (==4.7.1)
